open_rag_eval/__init__.py
open_rag_eval/_version.py
open_rag_eval/cli.py
open_rag_eval/plot_results.py
open_rag_eval/rag_results_loader.py
open_rag_eval/run_eval.py
open_rag_eval/run_query_generation.py
open_rag_eval/run_server.py
open_rag_eval/api/__init__.py
open_rag_eval/api/schemas.py
open_rag_eval/api/server.py
open_rag_eval/connectors/__init__.py
open_rag_eval/connectors/connector.py
open_rag_eval/connectors/langchain_connector.py
open_rag_eval/connectors/llama_index_connector.py
open_rag_eval/connectors/vectara_connector.py
open_rag_eval/data_classes/__init__.py
open_rag_eval/data_classes/eval_scores.py
open_rag_eval/data_classes/rag_results.py
open_rag_eval/evaluators/__init__.py
open_rag_eval/evaluators/base_evaluator.py
open_rag_eval/evaluators/consistency_evaluator.py
open_rag_eval/evaluators/golden_answer_evaluator.py
open_rag_eval/evaluators/trec_evaluator.py
open_rag_eval/metrics/__init__.py
open_rag_eval/metrics/autonugget_metric.py
open_rag_eval/metrics/base_metrics.py
open_rag_eval/metrics/bert_score_similarity_metric.py
open_rag_eval/metrics/citation_metric.py
open_rag_eval/metrics/factuality_backends.py
open_rag_eval/metrics/golden_answer_metrics.py
open_rag_eval/metrics/hallucination_metric.py
open_rag_eval/metrics/no_answer_metric.py
open_rag_eval/metrics/rouge_score_similarity_metric.py
open_rag_eval/metrics/umbrela_metric.py
open_rag_eval/models/__init__.py
open_rag_eval/models/embedding_models.py
open_rag_eval/models/llm_judges.py
open_rag_eval/query_generation/__init__.py
open_rag_eval/query_generation/base_generator.py
open_rag_eval/query_generation/document_sources.py
open_rag_eval/query_generation/llm_generator.py
open_rag_eval/query_generation/output_formatter.py
open_rag_eval/utils/__init__.py
open_rag_eval/utils/constants.py
open_rag_eval/viz/__init__.py
open_rag_eval/viz/visualize.py
open_rag_eval-0.3.0.dist-info/licenses/LICENSE
open_rag_eval-0.3.0.dist-info/METADATA
open_rag_eval-0.3.0.dist-info/WHEEL
open_rag_eval-0.3.0.dist-info/entry_points.txt
open_rag_eval-0.3.0.dist-info/top_level.txt
open_rag_eval-0.3.0.dist-info/RECORD
