Metadata-Version: 2.4
Name: open-rag-eval
Version: 0.3.0
Summary: A Python package for RAG Evaluation
Home-page: https://github.com/vectara/open-rag-eval
Author: Suleman Kazi
Author-email: suleman@vectara.com
Project-URL: Documentation, https://vectara.github.io/open-rag-eval/
Keywords: RAG,Evaluation,RAG evaluation,Vectara
Classifier: Programming Language :: Python :: 3
Classifier: License :: OSI Approved :: Apache Software License
Classifier: Operating System :: OS Independent
Classifier: Development Status :: 4 - Beta
Classifier: Topic :: Scientific/Engineering :: Artificial Intelligence
Classifier: Topic :: Software Development :: Libraries :: Python Modules
Requires-Python: >=3.9
License-File: LICENSE
Requires-Dist: flask==3.0.3
Requires-Dist: Flask-Cors>=4.0.2
Requires-Dist: langchain>=1.0.3
Requires-Dist: langchain_chroma>=1.0.0
Requires-Dist: langchain_openai>=1.0.3
Requires-Dist: langchain_community>=0.4.1
Requires-Dist: llama_index>=0.14.8
Requires-Dist: matplotlib~=3.10.1
Requires-Dist: numpy~=2.2.4
Requires-Dist: omegaconf~=2.3.0
Requires-Dist: openai~=2.7.2
Requires-Dist: google-genai~=1.50.1
Requires-Dist: anthropic~=0.72.1
Requires-Dist: together~=1.5.30
Requires-Dist: pandas==2.2.3
Requires-Dist: pydantic==2.11.7
Requires-Dist: python-dotenv~=1.0.1
Requires-Dist: requests~=2.32.3
Requires-Dist: seaborn~=0.13.2
Requires-Dist: setuptools>=70.0.0
Requires-Dist: streamlit>=1.49.1
Requires-Dist: tenacity~=9.1.2
Requires-Dist: torch==2.7.1
Requires-Dist: tqdm==4.67.1
Requires-Dist: transformers==4.50.2
Requires-Dist: unstructured>=0.17.2
Requires-Dist: unstructured[pdf]>=0.17.2
Requires-Dist: rouge>=1.0.0
Requires-Dist: torchmetrics>=1.0.0
Dynamic: author
Dynamic: author-email
Dynamic: classifier
Dynamic: description
Dynamic: description-content-type
Dynamic: home-page
Dynamic: keywords
Dynamic: license-file
Dynamic: project-url
Dynamic: requires-dist
Dynamic: requires-python
Dynamic: summary
